scGALA/__init__.py
scGALA/data.py
scGALA/main.py
scGALA/model.py
scGALA/utils.py
scgala-0.5.0.dist-info/LICENSE
scgala-0.5.0.dist-info/METADATA
scgala-0.5.0.dist-info/WHEEL
scgala-0.5.0.dist-info/top_level.txt
scgala-0.5.0.dist-info/RECORD
