Metadata-Version: 2.2
Name: scGALA
Version: 0.5.0
Summary: scGALA: Graph Link Prediction Based Cell Alignment for Comprehensive Data Integration
Home-page: https://github.com/mcgilldinglab/scGALA
Author: Guo Jiang
Author-email: guo.jiang@mail.mcgill.ca
License: MIT
Classifier: Intended Audience :: Science/Research
Classifier: Operating System :: POSIX :: Linux
Classifier: Programming Language :: Python :: 3.10
License-File: LICENSE
Requires-Dist: scanpy[leiden]
Requires-Dist: torch_geometric
Requires-Dist: lightning
Requires-Dist: hnswlib
Requires-Dist: ipykernel
Requires-Dist: pot
Dynamic: author
Dynamic: author-email
Dynamic: classifier
Dynamic: home-page
Dynamic: license
Dynamic: requires-dist
Dynamic: summary
